[{"id":"9113072001","district_id":"911307","name":"Samenage"},{"id":"9113072002","district_id":"911307","name":"Haleroma"},{"id":"9113072003","district_id":"911307","name":"Muke"},{"id":"9113072004","district_id":"911307","name":"Pona"},{"id":"9113072005","district_id":"911307","name":"Ison"},{"id":"9113072006","district_id":"911307","name":"Asotapo"},{"id":"9113072007","district_id":"911307","name":"Hirin"},{"id":"9113072008","district_id":"911307","name":"Notnarek"},{"id":"9113072009","district_id":"911307","name":"Hugilokon"}]