[{"id":"9114412001","district_id":"911441","name":"Peyola"},{"id":"9114412002","district_id":"911441","name":"Kogotime"},{"id":"9114412003","district_id":"911441","name":"Gabunam"},{"id":"9114412004","district_id":"911441","name":"Gulak"},{"id":"9114412005","district_id":"911441","name":"Melaga"},{"id":"9114412006","district_id":"911441","name":"Ekoni"},{"id":"9114412007","district_id":"911441","name":"Minggen"},{"id":"9114412008","district_id":"911441","name":"Kandimbaga"},{"id":"9114412009","district_id":"911441","name":"Kinebe"},{"id":"9114412010","district_id":"911441","name":"Belela"}]